ntopng/historical.py
ntopng/host.py
ntopng/interface.py
ntopng/logo.py
ntopng/ntopng.py
ntopng/report.py
ntopng-6.1.240321.dist-info/METADATA
ntopng-6.1.240321.dist-info/WHEEL
ntopng-6.1.240321.dist-info/top_level.txt
ntopng-6.1.240321.dist-info/RECORD
